parservk/__init__.py
parservk/baseclass.py
parservk/classes.py
parservk/correctionclass.py
parservk/logger.py
parservk/models.py
parservk/version.py
parservk-1.0.dist-info/METADATA
parservk-1.0.dist-info/WHEEL
parservk-1.0.dist-info/top_level.txt
parservk-1.0.dist-info/RECORD
