Metadata-Version: 2.1
Name: parservk
Version: 1.0
License: MIT
Requires-Dist: requests ==2.31.0
Requires-Dist: grequests ==0.7.0
